Coffee/__init__.py
Coffee/CLI/__init__.py
Coffee/CLI/coffee.py
Coffee/CLI/coffeed.py
Coffee/Core/Diagnose.py
Coffee/Core/NtpSync.py
Coffee/Core/Playbook.py
Coffee/Core/Plugin.py
Coffee/Core/Settings.py
Coffee/Core/Utils.py
Coffee/Core/__init__.py
Coffee/Data/DataExtractor.py
Coffee/Data/DataFlow.py
Coffee/Data/DataLoader.py
Coffee/Data/DataModel.py
Coffee/Data/DataStore.py
Coffee/Data/DataViz.py
Coffee/Data/Database.py
Coffee/Data/PatternMatchReport.py
Coffee/Data/Processors.py
Coffee/Data/TimestampPatterns.py
Coffee/Data/__init__.py
Coffee/Logkit/LogWatchDog.py
Coffee/Logkit/__init__.py
Coffee/Logkit/utils/LogTail.py
Coffee/Logkit/utils/__init__.py
Coffee/Network/NetworkEmulator.py
Coffee/Network/__init__.py
Coffee/Playbook/__init__.py
Coffee/Playbook/PowerToys/__init__.py
Coffee/Service/__init__.py
Coffee/Service/settings.py
Coffee/Service/urls.py
Coffee/ServiceApp/__init__.py
Coffee/ServiceApp/MainApp/__init__.py
Coffee/ServiceApp/MainApp/admin.py
Coffee/ServiceApp/MainApp/apps.py
Coffee/ServiceApp/MainApp/models.py
Coffee/ServiceApp/MainApp/tests.py
Coffee/ServiceApp/MainApp/urls.py
Coffee/ServiceApp/MainApp/views.py
Coffee/ServiceApp/MainApp/migrations/__init__.py
CoffeePlaybooks/__init__.py
pycoffee-1.0.6.dist-info/LICENSE
pycoffee-1.0.6.dist-info/METADATA
pycoffee-1.0.6.dist-info/WHEEL
pycoffee-1.0.6.dist-info/entry_points.txt
pycoffee-1.0.6.dist-info/top_level.txt
pycoffee-1.0.6.dist-info/zip-safe
pycoffee-1.0.6.dist-info/RECORD
