Metadata-Version: 2.1
Name: pycoffee
Version: 1.0.6
Summary: Programmers' tools. Enjoy Coffee time!
Author: tkorays
Author-email: tkorays <tkorays@hotmail.com>
License: Copyright (c) 2018 The Python Packaging Authority
Project-URL: Homepage, https://github.com/tkorays/pycoffee
Project-URL: Bug Tracker, https://github.com/tkorays/pycoffee/issues
Classifier: Programming Language :: Python :: 3
Classifier: License :: OSI Approved :: MIT License
Classifier: Operating System :: OS Independent
Requires-Python: >=3.7
License-File: LICENSE
Requires-Dist: pyyaml
Requires-Dist: click
Requires-Dist: influxdb
Requires-Dist: requests
Requires-Dist: wget
Requires-Dist: watchdog
Requires-Dist: rich
Requires-Dist: ntplib
Requires-Dist: grafanalib
Requires-Dist: flask
Requires-Dist: pid
Requires-Dist: python-daemon
Requires-Dist: django
Requires-Dist: h5py
Requires-Dist: numpy
Requires-Dist: ddt
